sip-6.15.0.dist-info/licenses/LICENSE
sipbuild/__init__.py
sipbuild/_version.py
sipbuild/abstract_builder.py
sipbuild/abstract_project.py
sipbuild/api.py
sipbuild/argument_parser.py
sipbuild/bindings.py
sipbuild/buildable.py
sipbuild/builder.py
sipbuild/configurable.py
sipbuild/distutils_builder.py
sipbuild/exceptions.py
sipbuild/installable.py
sipbuild/project.py
sipbuild/py_versions.py
sipbuild/pyproject.py
sipbuild/setuptools_builder.py
sipbuild/sip_module_configuration.py
sipbuild/toml.py
sipbuild/version.py
sipbuild/distinfo/__init__.py
sipbuild/distinfo/distinfo.py
sipbuild/generator/__init__.py
sipbuild/generator/bindings_configuration.py
sipbuild/generator/error_log.py
sipbuild/generator/indexed_lists.py
sipbuild/generator/instantiations.py
sipbuild/generator/python_slots.py
sipbuild/generator/scoped_name.py
sipbuild/generator/specification.py
sipbuild/generator/templates.py
sipbuild/generator/utils.py
sipbuild/generator/outputs/__init__.py
sipbuild/generator/outputs/api.py
sipbuild/generator/outputs/extracts.py
sipbuild/generator/outputs/pyi.py
sipbuild/generator/outputs/type_hints.py
sipbuild/generator/outputs/xml.py
sipbuild/generator/outputs/code/__init__.py
sipbuild/generator/outputs/code/code.py
sipbuild/generator/outputs/code/snippets.py
sipbuild/generator/outputs/code/utils.py
sipbuild/generator/outputs/code/backends/__init__.py
sipbuild/generator/outputs/code/backends/abstract_backend.py
sipbuild/generator/outputs/code/backends/v12v13.py
sipbuild/generator/outputs/formatters/__init__.py
sipbuild/generator/outputs/formatters/argument.py
sipbuild/generator/outputs/formatters/enum.py
sipbuild/generator/outputs/formatters/klass.py
sipbuild/generator/outputs/formatters/misc.py
sipbuild/generator/outputs/formatters/signature.py
sipbuild/generator/outputs/formatters/template.py
sipbuild/generator/outputs/formatters/value_list.py
sipbuild/generator/outputs/formatters/variable.py
sipbuild/generator/parser/__init__.py
sipbuild/generator/parser/annotations.py
sipbuild/generator/parser/parser.py
sip-6.15.0.dist-info/METADATA
sip-6.15.0.dist-info/WHEEL
sip-6.15.0.dist-info/entry_points.txt
sip-6.15.0.dist-info/top_level.txt
sip-6.15.0.dist-info/RECORD
