Metadata-Version: 2.4
Name: sip
Version: 6.15.0
Summary: A Python bindings generator for C/C++ libraries
Author-email: Phil Thompson <phil@riverbankcomputing.com>
License-Expression: BSD-2-Clause
Project-URL: homepage, https://github.com/Python-SIP/sip
Requires-Python: >=3.10
License-File: LICENSE
Requires-Dist: packaging>=24.2
Requires-Dist: setuptools>=75.8.1
Requires-Dist: tomli; python_version < "3.11"
Dynamic: license-file
